buzzapi/__init__.py
buzzapi/client.py
buzzapi/resources/__init__.py
buzzapi/resources/entity_gradebook_2.py
buzzapi/resources/user_activity_stream.py
buzzapi-0.1.1.dist-info/LICENSE
buzzapi-0.1.1.dist-info/METADATA
buzzapi-0.1.1.dist-info/WHEEL
buzzapi-0.1.1.dist-info/RECORD
