Metadata-Version: 2.1
Name: buzzapi
Version: 0.1.1
Summary: 
Author: Zach Grammon
Author-email: zachgrammon@gmail.com
Requires-Python: >=3.10,<4.0
Classifier: Programming Language :: Python :: 3
Classifier: Programming Language :: Python :: 3.10
Classifier: Programming Language :: Python :: 3.11
Requires-Dist: python-dotenv (>=1.0.0,<2.0.0)
Requires-Dist: requests (>=2.28.2,<3.0.0)
